drfauto/__init__.py
drfauto/apps.py
drfauto/dynamic.py
drfauto/writer.py
drfauto/management/__init__.py
drfauto/management/commands/__init__.py
drfauto/management/commands/makefilter.py
drfauto/management/commands/makeserializer.py
drfauto/management/commands/makeview.py
drfauto/management/commands/core/__init__.py
drfauto/management/commands/core/command.py
drfauto/management/commands/core/file_writer.py
drfauto/management/commands/core/urlwriter.py
drfauto-1.6.0.dist-info/METADATA
drfauto-1.6.0.dist-info/WHEEL
drfauto-1.6.0.dist-info/top_level.txt
drfauto-1.6.0.dist-info/RECORD
