Metadata-Version: 2.1
Name: drfauto
Version: 1.6.0
Summary: Package for auto creating serializers, filters and views for Django models
Home-page: https://github.com/PasNA6713/drf-auto
Author: PasNA6713
Author-email: diementros@gmail.com
License: UNKNOWN
Platform: UNKNOWN
Requires-Dist: django
Requires-Dist: djangorestframework
Requires-Dist: django-filter
